netbox_vcenter/__init__.py
netbox_vcenter/background_tasks.py
netbox_vcenter/forms.py
netbox_vcenter/models.py
netbox_vcenter/navigation.py
netbox_vcenter/template_content.py
netbox_vcenter/urls.py
netbox_vcenter/validators.py
netbox_vcenter/views.py
netbox_vcenter/management/__init__.py
netbox_vcenter/management/commands/__init__.py
netbox_vcenter/management/commands/update_vcenter_cache.py
netbox_vcenter/migrations/0001_initial.py
netbox_vcenter/migrations/0002_auto_20200403_0215.py
netbox_vcenter/migrations/__init__.py
netbox_vcenter/templates/netbox_vcenter/cluster/vcenter_info.html
netbox_vcenter/templates/netbox_vcenter/virtualmachine/vcenter_refresh.html
netbox_vcenter/templates/netbox_vcenter/virtualmachine/vcenter_resources.html
netbox_vcenter-0.1.1.dist-info/LICENSE.txt
netbox_vcenter-0.1.1.dist-info/METADATA
netbox_vcenter-0.1.1.dist-info/WHEEL
netbox_vcenter-0.1.1.dist-info/top_level.txt
netbox_vcenter-0.1.1.dist-info/RECORD
